MANIFEST.in
README.md
requirements.txt
setup.py
django_admin_fix_ie_compatible/__init__.py
django_admin_fix_ie_compatible/admin.py
django_admin_fix_ie_compatible/apps.py
django_admin_fix_ie_compatible/models.py
django_admin_fix_ie_compatible/tests.py
django_admin_fix_ie_compatible/views.py
django_admin_fix_ie_compatible.egg-info/PKG-INFO
django_admin_fix_ie_compatible.egg-info/SOURCES.txt
django_admin_fix_ie_compatible.egg-info/dependency_links.txt
django_admin_fix_ie_compatible.egg-info/not-zip-safe
django_admin_fix_ie_compatible.egg-info/requires.txt
django_admin_fix_ie_compatible.egg-info/top_level.txt
django_admin_fix_ie_compatible/migrations/__init__.py
django_admin_fix_ie_compatible/templates/admin/base.html