Metadata-Version: 2.1
Name: django-admin-fix-ie-compatible
Version: 0.1.1
Summary: Add X-UA-Compatible meta to django's admin site, so that the admin site can work in IE's compatible mode under IE9 or high version.
Home-page: UNKNOWN
Author: zencore
Author-email: dobetter@zencore.cn
License: MIT
Keywords: django admin extentions,django admin fix ie compatible
Platform: UNKNOWN
Classifier: Development Status :: 5 - Production/Stable
Classifier: Intended Audience :: Developers
Classifier: Topic :: Software Development :: Libraries :: Python Modules
Classifier: License :: OSI Approved :: MIT License
Classifier: Programming Language :: Python :: 3
Classifier: Programming Language :: Python :: 3 :: Only
